framework/__init__.py
framework/astra.py
framework/agents/__init__.py
framework/agents/agent.py
framework/agents/exceptions.py
framework/agents/execution.py
framework/agents/retry.py
framework/agents/tool.py
framework/code_mode/__init__.py
framework/code_mode/api_generator.py
framework/code_mode/sandbox.py
framework/code_mode/tool_registry.py
framework/guardrails/__init__.py
framework/guardrails/base.py
framework/guardrails/content.py
framework/guardrails/exceptions.py
framework/guardrails/injection.py
framework/guardrails/pii.py
framework/guardrails/secrets.py
framework/mcp/__init__.py
framework/mcp/client.py
framework/mcp/exceptions.py
framework/mcp/manager.py
framework/mcp/registry.py
framework/mcp/server.py
framework/mcp/transport.py
framework/mcp/utils.py
framework/memory/COGNITIVE_MEMORY_SYSTEM.md
framework/memory/LTM_ANALYSIS.md
framework/memory/__init__.py
framework/memory/manager.py
framework/memory/memory.py
framework/memory/persistent_facts.py
framework/memory/token_counter.py
framework/middlewares/__init__.py
framework/middlewares/base.py
framework/middlewares/context.py
framework/middlewares/exceptions.py
framework/models/__init__.py
framework/models/__init__.pyi
framework/models/base.py
framework/models/aws/__init__.py
framework/models/aws/bedrock.py
framework/models/aws/bedrock_errors.py
framework/models/aws/bedrock_types.py
framework/models/google/gemini.py
framework/models/google/gemini.pyi
framework/models/huggingface/__init__.py
framework/models/huggingface/local.py
framework/rag/README.md
framework/rag/__init__.py
framework/rag/context.py
framework/rag/exceptions.py
framework/rag/pipeline.py
framework/rag/chunking/__init__.py
framework/rag/chunking/base.py
framework/rag/chunking/recursive.py
framework/rag/embedders/__init__.py
framework/rag/embedders/base.py
framework/rag/embedders/huggingface.py
framework/rag/embedders/openai.py
framework/rag/readers/__init__.py
framework/rag/readers/base.py
framework/rag/readers/factory.py
astra_framework-0.1.1.dist-info/METADATA
astra_framework-0.1.1.dist-info/WHEEL
astra_framework-0.1.1.dist-info/licenses/LICENSE
astra_framework-0.1.1.dist-info/RECORD
