Metadata-Version: 2.4
Name: astra-framework
Version: 0.1.1
Summary: Astra Framework - Core APIs and abstractions for building AI agents, teams, RAG pipelines, and workflows
Project-URL: Homepage, https://github.com/HeeManSu/astra-agi
Project-URL: Documentation, https://github.com/HeeManSu/astra-agi#readme
Project-URL: Repository, https://github.com/HeeManSu/astra-agi
Project-URL: Issues, https://github.com/HeeManSu/astra-agi/issues
Author-email: Himanshu Sharma <himanshu.kumarr07@gmail.com>
License: MIT
License-File: LICENSE
Keywords: agents,ai,ai-agents,framework,langchain-alternative,llm,multi-agent,rag,retrieval-augmented-generation
Classifier: Development Status :: 4 - Beta
Classifier: Intended Audience :: Developers
Classifier: License :: OSI Approved :: MIT License
Classifier: Programming Language :: Python :: 3
Classifier: Programming Language :: Python :: 3.10
Classifier: Programming Language :: Python :: 3.11
Classifier: Programming Language :: Python :: 3.12
Classifier: Programming Language :: Python :: 3.13
Classifier: Topic :: Scientific/Engineering :: Artificial Intelligence
Classifier: Typing :: Typed
Requires-Python: <3.14,>=3.10
Requires-Dist: accelerate>=0.26.0
Requires-Dist: aiohttp>=3.9.0
Requires-Dist: aiosqlite>=0.19.0
Requires-Dist: astra-observability>=0.1.0
Requires-Dist: google-genai>=1.0.0
Requires-Dist: greenlet>=3.0.0
Requires-Dist: httpx>=0.27.0
Requires-Dist: huggingface-hub>=0.20.0
Requires-Dist: lancedb>=0.4.0
Requires-Dist: motor>=3.3.0
Requires-Dist: openai>=1.0.0
Requires-Dist: pyarrow>=14.0.0
Requires-Dist: pydantic-settings>=2.0.0
Requires-Dist: pydantic>=2.0.0
Requires-Dist: python-dotenv>=1.0.0
Requires-Dist: sqlalchemy>=2.0.0
Requires-Dist: tiktoken>=0.5.0
Requires-Dist: torch>=2.0.0
Requires-Dist: transformers>=4.37.0
Provides-Extra: all
Requires-Dist: aioboto3>=12.0.0; extra == 'all'
Requires-Dist: beanie>=1.24.0; extra == 'all'
Requires-Dist: boto3>=1.35.0; extra == 'all'
Requires-Dist: motor>=3.3.0; extra == 'all'
Provides-Extra: aws
Requires-Dist: aioboto3>=12.0.0; extra == 'aws'
Requires-Dist: boto3>=1.35.0; extra == 'aws'
Provides-Extra: mongodb
Requires-Dist: beanie>=1.24.0; extra == 'mongodb'
Requires-Dist: motor>=3.3.0; extra == 'mongodb'
